[
  {
    "TeamLogoPath": "Europe\\Portugal\\2nd Tier\\Liga Portugal\\Benfica",
    "Continent": "Europe",
    "Country": "Portugal",
    "Name": "Benfica",
    "League": "Liga Portugal",
    "Attack": 79,
    "Mid": 80,
    "Defense": 79,
    "OverAll": 79,
    "Rating": 4.5
  },
  {
    "TeamLogoPath": "Europe\\Portugal\\2nd Tier\\Liga Portugal\\FC Porto",
    "Continent": "Europe",
    "Country": "Portugal",
    "Name": "FC Porto",
    "League": "Liga Portugal",
    "Attack": 80,
    "Mid": 77,
    "Defense": 75,
    "OverAll": 77,
    "Rating": 4.0
  },
  {
    "TeamLogoPath": "Europe\\Portugal\\2nd Tier\\Liga Portugal\\Sporting CP",
    "Continent": "Europe",
    "Country": "Portugal",
    "Name": "Sporting CP",
    "League": "Liga Portugal",
    "Attack": 80,
    "Mid": 78,
    "Defense": 77,
    "OverAll": 78,
    "Rating": 4.0
  },
  {
    "TeamLogoPath": "Europe\\Portugal\\2nd Tier\\Liga Portugal\\Vitória de Guimarães",
    "Continent": "Europe",
    "Country": "Portugal",
    "Name": "Vitória de Guimarães",
    "League": "Liga Portugal",
    "Attack": 73,
    "Mid": 71,
    "Defense": 71,
    "OverAll": 71,
    "Rating": 3.5
  },
  {
    "TeamLogoPath": "Europe\\Portugal\\2nd Tier\\Liga Portugal\\Boavista",
    "Continent": "Europe",
    "Country": "Portugal",
    "Name": "Boavista",
    "League": "Liga Portugal",
    "Attack": 71,
    "Mid": 70,
    "Defense": 71,
    "OverAll": 70,
    "Rating": 3.0
  },
  {
    "TeamLogoPath": "Europe\\Portugal\\2nd Tier\\Liga Portugal\\Braga",
    "Continent": "Europe",
    "Country": "Portugal",
    "Name": "Braga",
    "League": "Liga Portugal",
    "Attack": 78,
    "Mid": 76,
    "Defense": 75,
    "OverAll": 76,
    "Rating": 4.0
  },
  {
    "TeamLogoPath": "Europe\\Portugal\\2nd Tier\\Liga Portugal\\Rio Ave",
    "Continent": "Europe",
    "Country": "Portugal",
    "Name": "Rio Ave",
    "League": "Liga Portugal",
    "Attack": 71,
    "Mid": 69,
    "Defense": 71,
    "OverAll": 70,
    "Rating": 3.0
  },
  {
    "TeamLogoPath": "Europe\\Portugal\\2nd Tier\\Liga Portugal\\Chaves",
    "Continent": "Europe",
    "Country": "Portugal",
    "Name": "Chaves",
    "League": "Liga Portugal",
    "Attack": 70,
    "Mid": 69,
    "Defense": 69,
    "OverAll": 69,
    "Rating": 3.0
  },
  {
    "TeamLogoPath": "Europe\\Portugal\\2nd Tier\\Liga Portugal\\Moreirense",
    "Continent": "Europe",
    "Country": "Portugal",
    "Name": "Moreirense",
    "League": "Liga Portugal",
    "Attack": 68,
    "Mid": 70,
    "Defense": 69,
    "OverAll": 69,
    "Rating": 3.0
  },
  {
    "TeamLogoPath": "Europe\\Portugal\\2nd Tier\\Liga Portugal\\Portimonense",
    "Continent": "Europe",
    "Country": "Portugal",
    "Name": "Portimonense",
    "League": "Liga Portugal",
    "Attack": 68,
    "Mid": 69,
    "Defense": 69,
    "OverAll": 69,
    "Rating": 3.0
  },
  {
    "TeamLogoPath": "Europe\\Portugal\\2nd Tier\\Liga Portugal\\Famalicão",
    "Continent": "Europe",
    "Country": "Portugal",
    "Name": "Famalicão",
    "League": "Liga Portugal",
    "Attack": 70,
    "Mid": 70,
    "Defense": 70,
    "OverAll": 70,
    "Rating": 3.0
  },
  {
    "TeamLogoPath": "Europe\\Portugal\\2nd Tier\\Liga Portugal\\Estrela Amadora",
    "Continent": "Europe",
    "Country": "Portugal",
    "Name": "Estrela Amadora",
    "League": "Liga Portugal",
    "Attack": 69,
    "Mid": 67,
    "Defense": 69,
    "OverAll": 69,
    "Rating": 3.0
  },
  {
    "TeamLogoPath": "Europe\\Portugal\\2nd Tier\\Liga Portugal\\Estoril",
    "Continent": "Europe",
    "Country": "Portugal",
    "Name": "Estoril",
    "League": "Liga Portugal",
    "Attack": 70,
    "Mid": 69,
    "Defense": 71,
    "OverAll": 70,
    "Rating": 3.0
  },
  {
    "TeamLogoPath": "Europe\\Portugal\\2nd Tier\\Liga Portugal\\Gil Vicente FC",
    "Continent": "Europe",
    "Country": "Portugal",
    "Name": "Gil Vicente FC",
    "League": "Liga Portugal",
    "Attack": 66,
    "Mid": 70,
    "Defense": 69,
    "OverAll": 70,
    "Rating": 3.0
  },
  {
    "TeamLogoPath": "Europe\\Portugal\\2nd Tier\\Liga Portugal\\Casa Pia",
    "Continent": "Europe",
    "Country": "Portugal",
    "Name": "Casa Pia",
    "League": "Liga Portugal",
    "Attack": 70,
    "Mid": 68,
    "Defense": 69,
    "OverAll": 69,
    "Rating": 3.0
  },
  {
    "TeamLogoPath": "Europe\\Portugal\\2nd Tier\\Liga Portugal\\Arouca",
    "Continent": "Europe",
    "Country": "Portugal",
    "Name": "Arouca",
    "League": "Liga Portugal",
    "Attack": 74,
    "Mid": 70,
    "Defense": 69,
    "OverAll": 70,
    "Rating": 3.0
  },
  {
    "TeamLogoPath": "Europe\\Portugal\\2nd Tier\\Liga Portugal\\Vizela",
    "Continent": "Europe",
    "Country": "Portugal",
    "Name": "Vizela",
    "League": "Liga Portugal",
    "Attack": 69,
    "Mid": 69,
    "Defense": 67,
    "OverAll": 68,
    "Rating": 2.5
  },
  {
    "TeamLogoPath": "Europe\\Portugal\\2nd Tier\\Liga Portugal\\Farense",
    "Continent": "Europe",
    "Country": "Portugal",
    "Name": "Farense",
    "League": "Liga Portugal",
    "Attack": 70,
    "Mid": 70,
    "Defense": 68,
    "OverAll": 69,
    "Rating": 3.0
  }
]